./.gitignore
./Dockerfile
./LICENSE
./PKG-INFO
./README.md
./README_LEGACY.md
./docker-compose.yml
./kospi_kosdaq_stock_server.py
./krx_data_client.py
./pyproject.toml
./requirements.txt
./smithery.yaml
./uv.lock
./.claude/settings.local.json
kospi_kosdaq_stock_server-0.3.37.dist-info/METADATA
kospi_kosdaq_stock_server-0.3.37.dist-info/WHEEL
kospi_kosdaq_stock_server-0.3.37.dist-info/entry_points.txt
kospi_kosdaq_stock_server-0.3.37.dist-info/licenses/LICENSE
kospi_kosdaq_stock_server-0.3.37.dist-info/RECORD
