Metadata-Version: 2.4
Name: kospi-kosdaq-stock-server
Version: 0.3.37
Summary: KOSPI/KOSDAQ Stock Data MCP Server with KRX Data Marketplace integration
Project-URL: Homepage, https://github.com/dragon1086/kospi-kosdaq-stock-server
Project-URL: Repository, https://github.com/dragon1086/kospi-kosdaq-stock-server
Project-URL: Issues, https://github.com/dragon1086/kospi-kosdaq-stock-server/issues
Author-email: Sangrok Mun <munsangrok@gmail.com>
License: MIT
License-File: LICENSE
Keywords: finance,korea,kosdaq,kospi,krx,mcp,stock
Classifier: Development Status :: 4 - Beta
Classifier: License :: OSI Approved :: MIT License
Classifier: Programming Language :: Python :: 3
Classifier: Programming Language :: Python :: 3.10
Classifier: Programming Language :: Python :: 3.11
Classifier: Programming Language :: Python :: 3.12
Classifier: Topic :: Office/Business :: Financial :: Investment
Requires-Python: >=3.10
Requires-Dist: holidays>=0.40
Requires-Dist: mcp>=0.1.0
Requires-Dist: nest-asyncio>=1.5.0
Requires-Dist: pandas>=1.5.0
Requires-Dist: playwright>=1.40.0
Requires-Dist: requests>=2.28.0
Provides-Extra: dev
Requires-Dist: pytest-asyncio>=0.21.0; extra == 'dev'
Requires-Dist: pytest>=7.0.0; extra == 'dev'
Provides-Extra: legacy
Requires-Dist: pykrx>=1.0.0; extra == 'legacy'
